[
  {
    "__type__": "cc.Prefab",
    "_name": "myInfoItem",
    "_objFlags": 0,
    "_native": "",
    "data": {
      "__id__": 1
    },
    "optimizationPolicy": 0,
    "asyncLoadAssets": false
  },
  {
    "__type__": "cc.Node",
    "_name": "Canvas",
    "_objFlags": 0,
    "_parent": null,
    "_children": [
      {
        "__id__": 2
      },
      {
        "__id__": 5
      },
      {
        "__id__": 11
      },
      {
        "__id__": 17
      }
    ],
    "_active": true,
    "_level": 1,
    "_components": [
      {
        "__id__": 21
      }
    ],
    "_prefab": {
      "__id__": 22
    },
    "_opacity": 255,
    "_color": {
      "__type__": "cc.Color",
      "r": 255,
      "g": 255,
      "b": 255,
      "a": 255
    },
    "_contentSize": {
      "__type__": "cc.Size",
      "width": 640,
      "height": 60
    },
    "_anchorPoint": {
      "__type__": "cc.Vec2",
      "x": 0.5,
      "y": 0.5
    },
    "_position": {
      "__type__": "cc.Vec3",
      "x": 0,
      "y": 0,
      "z": 0
    },
    "_scale": {
      "__type__": "cc.Vec3",
      "x": 1,
      "y": 1,
      "z": 1
    },
    "_rotationX": 0,
    "_rotationY": 0,
    "_quat": {
      "__type__": "cc.Quat",
      "x": 0,
      "y": 0,
      "z": 0,
      "w": 1
    },
    "_skewX": 0,
    "_skewY": 0,
    "_zIndex": 0,
    "groupIndex": 0,
    "_id": ""
  },
  {
    "__type__": "cc.Node",
    "_name": "money",
    "_objFlags": 0,
    "_parent": {
      "__id__": 1
    },
    "_children": [],
    "_active": true,
    "_level": 2,
    "_components": [
      {
        "__id__": 3
      }
    ],
    "_prefab": {
      "__id__": 4
    },
    "_opacity": 255,
    "_color": {
      "__type__": "cc.Color",
      "r": 191,
      "g": 95,
      "b": 2,
      "a": 255
    },
    "_contentSize": {
      "__type__": "cc.Size",
      "width": 80.05,
      "height": 40
    },
    "_anchorPoint": {
      "__type__": "cc.Vec2",
      "x": 0.5,
      "y": 0.5
    },
    "_position": {
      "__type__": "cc.Vec3",
      "x": -200,
      "y": 0,
      "z": 0
    },
    "_scale": {
      "__type__": "cc.Vec3",
      "x": 1,
      "y": 1,
      "z": 1
    },
    "_rotationX": 0,
    "_rotationY": 0,
    "_quat": {
      "__type__": "cc.Quat",
      "x": 0,
      "y": 0,
      "z": 0,
      "w": 1
    },
    "_skewX": 0,
    "_skewY": 0,
    "_zIndex": 0,
    "groupIndex": 0,
    "_id": ""
  },
  {
    "__type__": "cc.Label",
    "_name": "",
    "_objFlags": 0,
    "node": {
      "__id__": 2
    },
    "_enabled": true,
    "_srcBlendFactor": 1,
    "_dstBlendFactor": 771,
    "_useOriginalSize": false,
    "_string": "100元",
    "_N$string": "100元",
    "_fontSize": 30,
    "_lineHeight": 40,
    "_enableWrapText": true,
    "_N$file": null,
    "_isSystemFontUsed": true,
    "_spacingX": 0,
    "_N$horizontalAlign": 1,
    "_N$verticalAlign": 1,
    "_N$fontFamily": "Arial",
    "_N$overflow": 0,
    "_id": ""
  },
  {
    "__type__": "cc.PrefabInfo",
    "root": {
      "__id__": 1
    },
    "asset": {
      "__uuid__": "8bbae9f1-a749-43f3-a56a-1de931855fa9"
    },
    "fileId": "e5Aujv0/VPJLPQzgd0Sckf",
    "sync": false
  },
  {
    "__type__": "cc.Node",
    "_name": "head_1",
    "_objFlags": 0,
    "_parent": {
      "__id__": 1
    },
    "_children": [
      {
        "__id__": 6
      }
    ],
    "_active": true,
    "_level": 2,
    "_components": [
      {
        "__id__": 9
      }
    ],
    "_prefab": {
      "__id__": 10
    },
    "_opacity": 255,
    "_color": {
      "__type__": "cc.Color",
      "r": 255,
      "g": 255,
      "b": 255,
      "a": 255
    },
    "_contentSize": {
      "__type__": "cc.Size",
      "width": 50,
      "height": 50
    },
    "_anchorPoint": {
      "__type__": "cc.Vec2",
      "x": 0.5,
      "y": 0.5
    },
    "_position": {
      "__type__": "cc.Vec3",
      "x": 50,
      "y": -2,
      "z": 0
    },
    "_scale": {
      "__type__": "cc.Vec3",
      "x": 1,
      "y": 1,
      "z": 1
    },
    "_rotationX": 0,
    "_rotationY": 0,
    "_quat": {
      "__type__": "cc.Quat",
      "x": 0,
      "y": 0,
      "z": 0,
      "w": 1
    },
    "_skewX": 0,
    "_skewY": 0,
    "_zIndex": 0,
    "groupIndex": 0,
    "_id": ""
  },
  {
    "__type__": "cc.Node",
    "_name": "ren",
    "_objFlags": 0,
    "_parent": {
      "__id__": 5
    },
    "_children": [],
    "_active": true,
    "_level": 3,
    "_components": [
      {
        "__id__": 7
      }
    ],
    "_prefab": {
      "__id__": 8
    },
    "_opacity": 255,
    "_color": {
      "__type__": "cc.Color",
      "r": 255,
      "g": 255,
      "b": 255,
      "a": 255
    },
    "_contentSize": {
      "__type__": "cc.Size",
      "width": 33,
      "height": 30
    },
    "_anchorPoint": {
      "__type__": "cc.Vec2",
      "x": 0.5,
      "y": 0.5
    },
    "_position": {
      "__type__": "cc.Vec3",
      "x": 0,
      "y": 0,
      "z": 0
    },
    "_scale": {
      "__type__": "cc.Vec3",
      "x": 1,
      "y": 1,
      "z": 1
    },
    "_rotationX": 0,
    "_rotationY": 0,
    "_quat": {
      "__type__": "cc.Quat",
      "x": 0,
      "y": 0,
      "z": 0,
      "w": 1
    },
    "_skewX": 0,
    "_skewY": 0,
    "_zIndex": 0,
    "groupIndex": 0,
    "_id": ""
  },
  {
    "__type__": "cc.Sprite",
    "_name": "",
    "_objFlags": 0,
    "node": {
      "__id__": 6
    },
    "_enabled": true,
    "_srcBlendFactor": 770,
    "_dstBlendFactor": 771,
    "_spriteFrame": {
      "__uuid__": "fb29ac51-1b08-484e-8244-0d4c087ce27d"
    },
    "_type": 0,
    "_sizeMode": 1,
    "_fillType": 0,
    "_fillCenter": {
      "__type__": "cc.Vec2",
      "x": 0,
      "y": 0
    },
    "_fillStart": 0,
    "_fillRange": 0,
    "_isTrimmedMode": true,
    "_state": 0,
    "_atlas": null,
    "_id": ""
  },
  {
    "__type__": "cc.PrefabInfo",
    "root": {
      "__id__": 1
    },
    "asset": {
      "__uuid__": "8bbae9f1-a749-43f3-a56a-1de931855fa9"
    },
    "fileId": "0dgBqF03pPo6GQkqRY2VoT",
    "sync": false
  },
  {
    "__type__": "cc.Sprite",
    "_name": "",
    "_objFlags": 0,
    "node": {
      "__id__": 5
    },
    "_enabled": true,
    "_srcBlendFactor": 770,
    "_dstBlendFactor": 771,
    "_spriteFrame": {
      "__uuid__": "25ceb432-6b8c-46e4-812d-6b42ab4f1f0f"
    },
    "_type": 0,
    "_sizeMode": 0,
    "_fillType": 0,
    "_fillCenter": {
      "__type__": "cc.Vec2",
      "x": 0,
      "y": 0
    },
    "_fillStart": 0,
    "_fillRange": 0,
    "_isTrimmedMode": true,
    "_state": 0,
    "_atlas": null,
    "_id": ""
  },
  {
    "__type__": "cc.PrefabInfo",
    "root": {
      "__id__": 1
    },
    "asset": {
      "__uuid__": "8bbae9f1-a749-43f3-a56a-1de931855fa9"
    },
    "fileId": "7dP6VwHOFNULTKzqUjc5dY",
    "sync": false
  },
  {
    "__type__": "cc.Node",
    "_name": "head_2",
    "_objFlags": 0,
    "_parent": {
      "__id__": 1
    },
    "_children": [
      {
        "__id__": 12
      }
    ],
    "_active": true,
    "_level": 2,
    "_components": [
      {
        "__id__": 15
      }
    ],
    "_prefab": {
      "__id__": 16
    },
    "_opacity": 255,
    "_color": {
      "__type__": "cc.Color",
      "r": 255,
      "g": 255,
      "b": 255,
      "a": 255
    },
    "_contentSize": {
      "__type__": "cc.Size",
      "width": 50,
      "height": 50
    },
    "_anchorPoint": {
      "__type__": "cc.Vec2",
      "x": 0.5,
      "y": 0.5
    },
    "_position": {
      "__type__": "cc.Vec3",
      "x": -20,
      "y": -2,
      "z": 0
    },
    "_scale": {
      "__type__": "cc.Vec3",
      "x": 1,
      "y": 1,
      "z": 1
    },
    "_rotationX": 0,
    "_rotationY": 0,
    "_quat": {
      "__type__": "cc.Quat",
      "x": 0,
      "y": 0,
      "z": 0,
      "w": 1
    },
    "_skewX": 0,
    "_skewY": 0,
    "_zIndex": 0,
    "groupIndex": 0,
    "_id": ""
  },
  {
    "__type__": "cc.Node",
    "_name": "ren",
    "_objFlags": 0,
    "_parent": {
      "__id__": 11
    },
    "_children": [],
    "_active": true,
    "_level": 3,
    "_components": [
      {
        "__id__": 13
      }
    ],
    "_prefab": {
      "__id__": 14
    },
    "_opacity": 255,
    "_color": {
      "__type__": "cc.Color",
      "r": 255,
      "g": 255,
      "b": 255,
      "a": 255
    },
    "_contentSize": {
      "__type__": "cc.Size",
      "width": 33,
      "height": 30
    },
    "_anchorPoint": {
      "__type__": "cc.Vec2",
      "x": 0.5,
      "y": 0.5
    },
    "_position": {
      "__type__": "cc.Vec3",
      "x": 0,
      "y": 0,
      "z": 0
    },
    "_scale": {
      "__type__": "cc.Vec3",
      "x": 1,
      "y": 1,
      "z": 1
    },
    "_rotationX": 0,
    "_rotationY": 0,
    "_quat": {
      "__type__": "cc.Quat",
      "x": 0,
      "y": 0,
      "z": 0,
      "w": 1
    },
    "_skewX": 0,
    "_skewY": 0,
    "_zIndex": 0,
    "groupIndex": 0,
    "_id": ""
  },
  {
    "__type__": "cc.Sprite",
    "_name": "",
    "_objFlags": 0,
    "node": {
      "__id__": 12
    },
    "_enabled": true,
    "_srcBlendFactor": 770,
    "_dstBlendFactor": 771,
    "_spriteFrame": {
      "__uuid__": "fb29ac51-1b08-484e-8244-0d4c087ce27d"
    },
    "_type": 0,
    "_sizeMode": 1,
    "_fillType": 0,
    "_fillCenter": {
      "__type__": "cc.Vec2",
      "x": 0,
      "y": 0
    },
    "_fillStart": 0,
    "_fillRange": 0,
    "_isTrimmedMode": true,
    "_state": 0,
    "_atlas": null,
    "_id": ""
  },
  {
    "__type__": "cc.PrefabInfo",
    "root": {
      "__id__": 1
    },
    "asset": {
      "__uuid__": "8bbae9f1-a749-43f3-a56a-1de931855fa9"
    },
    "fileId": "71+9mhVBFM6L9ECM5vqvfr",
    "sync": false
  },
  {
    "__type__": "cc.Sprite",
    "_name": "",
    "_objFlags": 0,
    "node": {
      "__id__": 11
    },
    "_enabled": true,
    "_srcBlendFactor": 770,
    "_dstBlendFactor": 771,
    "_spriteFrame": {
      "__uuid__": "25ceb432-6b8c-46e4-812d-6b42ab4f1f0f"
    },
    "_type": 0,
    "_sizeMode": 0,
    "_fillType": 0,
    "_fillCenter": {
      "__type__": "cc.Vec2",
      "x": 0,
      "y": 0
    },
    "_fillStart": 0,
    "_fillRange": 0,
    "_isTrimmedMode": true,
    "_state": 0,
    "_atlas": null,
    "_id": ""
  },
  {
    "__type__": "cc.PrefabInfo",
    "root": {
      "__id__": 1
    },
    "asset": {
      "__uuid__": "8bbae9f1-a749-43f3-a56a-1de931855fa9"
    },
    "fileId": "9baxGL6sxLF6NW4C7gHOAM",
    "sync": false
  },
  {
    "__type__": "cc.Node",
    "_name": "btn_invite",
    "_objFlags": 0,
    "_parent": {
      "__id__": 1
    },
    "_children": [],
    "_active": true,
    "_level": 2,
    "_components": [
      {
        "__id__": 18
      },
      {
        "__id__": 19
      }
    ],
    "_prefab": {
      "__id__": 20
    },
    "_opacity": 255,
    "_color": {
      "__type__": "cc.Color",
      "r": 255,
      "g": 255,
      "b": 255,
      "a": 255
    },
    "_contentSize": {
      "__type__": "cc.Size",
      "width": 100,
      "height": 50
    },
    "_anchorPoint": {
      "__type__": "cc.Vec2",
      "x": 0.5,
      "y": 0.5
    },
    "_position": {
      "__type__": "cc.Vec3",
      "x": 250,
      "y": 0,
      "z": 0
    },
    "_scale": {
      "__type__": "cc.Vec3",
      "x": 1,
      "y": 1,
      "z": 1
    },
    "_rotationX": 0,
    "_rotationY": 0,
    "_quat": {
      "__type__": "cc.Quat",
      "x": 0,
      "y": 0,
      "z": 0,
      "w": 1
    },
    "_skewX": 0,
    "_skewY": 0,
    "_zIndex": 0,
    "groupIndex": 0,
    "_id": ""
  },
  {
    "__type__": "cc.Sprite",
    "_name": "",
    "_objFlags": 0,
    "node": {
      "__id__": 17
    },
    "_enabled": true,
    "_srcBlendFactor": 770,
    "_dstBlendFactor": 771,
    "_spriteFrame": {
      "__uuid__": "ed4a76eb-2898-4dd7-835f-3cbbcfec3af5"
    },
    "_type": 1,
    "_sizeMode": 0,
    "_fillType": 0,
    "_fillCenter": {
      "__type__": "cc.Vec2",
      "x": 0,
      "y": 0
    },
    "_fillStart": 0,
    "_fillRange": 0,
    "_isTrimmedMode": true,
    "_state": 0,
    "_atlas": null,
    "_id": ""
  },
  {
    "__type__": "cc.Button",
    "_name": "",
    "_objFlags": 0,
    "node": {
      "__id__": 17
    },
    "_enabled": true,
    "transition": 2,
    "pressedColor": {
      "__type__": "cc.Color",
      "r": 255,
      "g": 255,
      "b": 255,
      "a": 255
    },
    "hoverColor": {
      "__type__": "cc.Color",
      "r": 255,
      "g": 255,
      "b": 255,
      "a": 255
    },
    "duration": 0.1,
    "zoomScale": 1.2,
    "clickEvents": [],
    "_N$interactable": true,
    "_N$enableAutoGrayEffect": false,
    "_N$normalColor": {
      "__type__": "cc.Color",
      "r": 255,
      "g": 255,
      "b": 255,
      "a": 255
    },
    "_N$disabledColor": {
      "__type__": "cc.Color",
      "r": 255,
      "g": 255,
      "b": 255,
      "a": 255
    },
    "_N$normalSprite": {
      "__uuid__": "ed4a76eb-2898-4dd7-835f-3cbbcfec3af5"
    },
    "_N$pressedSprite": null,
    "pressedSprite": null,
    "_N$hoverSprite": null,
    "hoverSprite": null,
    "_N$disabledSprite": null,
    "_N$target": {
      "__id__": 17
    },
    "_id": ""
  },
  {
    "__type__": "cc.PrefabInfo",
    "root": {
      "__id__": 1
    },
    "asset": {
      "__uuid__": "8bbae9f1-a749-43f3-a56a-1de931855fa9"
    },
    "fileId": "74HeCI1rJLcIg/o2IeQa9D",
    "sync": false
  },
  {
    "__type__": "cc.Sprite",
    "_name": "",
    "_objFlags": 0,
    "node": {
      "__id__": 1
    },
    "_enabled": true,
    "_srcBlendFactor": 770,
    "_dstBlendFactor": 771,
    "_spriteFrame": {
      "__uuid__": "12163499-f748-448a-9a6b-25a1677ca65b"
    },
    "_type": 1,
    "_sizeMode": 0,
    "_fillType": 0,
    "_fillCenter": {
      "__type__": "cc.Vec2",
      "x": 0,
      "y": 0
    },
    "_fillStart": 0,
    "_fillRange": 0,
    "_isTrimmedMode": true,
    "_state": 0,
    "_atlas": null,
    "_id": ""
  },
  {
    "__type__": "cc.PrefabInfo",
    "root": {
      "__id__": 1
    },
    "asset": {
      "__uuid__": "8bbae9f1-a749-43f3-a56a-1de931855fa9"
    },
    "fileId": "95gmJr58hDCYmv6zn15wrC",
    "sync": false
  }
]